optipyzer/__init__.py
optipyzer/api.py
optipyzer/const.py
optipyzer/exceptions.py
optipyzer/helpers.py
optipyzer/log.py
optipyzer/models.py
optipyzer-0.4.1.dist-info/METADATA
optipyzer-0.4.1.dist-info/WHEEL
optipyzer-0.4.1.dist-info/top_level.txt
optipyzer-0.4.1.dist-info/RECORD
