Metadata-Version: 2.1
Name: optipyzer
Version: 0.4.1
Summary: Codon optimize DNA and Protein sequences for multiple species.
Home-page: https://github.com/NLeRoy917/optipyzer
Author: Nathan LeRoy
Author-email: NLeRoy917@gmail.com
License: Apache 2.0
Keywords: codon optimization dna protein biology bioinformatics
Classifier: Topic :: Software Development :: Libraries
Classifier: Operating System :: OS Independent
Classifier: License :: OSI Approved :: Apache Software License
Classifier: Programming Language :: Python
Classifier: Programming Language :: Python :: 3
Requires-Dist: requests
Requires-Dist: pydantic
